isnumbertool/__init__.py
isnumbertool/__main__.py
isnumbertool-0.1.0.dist-info/METADATA
isnumbertool-0.1.0.dist-info/WHEEL
isnumbertool-0.1.0.dist-info/entry_points.txt
isnumbertool-0.1.0.dist-info/top_level.txt
isnumbertool-0.1.0.dist-info/RECORD
