Metadata-Version: 2.4
Name: isnumbertool
Version: 0.1.0
Summary: a tool to check if input is num or not
Requires-Python: >=3.8
